{
  "total_restaurants": 107535,
  "unique_primary_types": 155,
  "primary_types": [
    "acai_shop",
    "afghani_restaurant",
    "african_restaurant",
    "american_restaurant",
    "amphitheatre",
    "amusement_center",
    "apartment_building",
    "apartment_complex",
    "arena",
    "art_gallery",
    "asian_grocery_store",
    "asian_restaurant",
    "athletic_field",
    "bagel_shop",
    "bakery",
    "banquet_hall",
    "bar",
    "bar_and_grill",
    "barbecue_restaurant",
    "book_store",
    "botanical_garden",
    "bowling_alley",
    "brazilian_restaurant",
    "breakfast_restaurant",
    "brunch_restaurant",
    "buffet_restaurant",
    "bus_station",
    "butcher_shop",
    "cafe",
    "cafeteria",
    "casino",
    "catering_service",
    "child_care_agency",
    "chinese_restaurant",
    "chocolate_shop",
    "clothing_store",
    "coffee_shop",
    "comedy_club",
    "concert_hall",
    "condominium_complex",
    "confectionery",
    "consultant",
    "convenience_store",
    "corporate_office",
    "courier_service",
    "cultural_center",
    "deli",
    "dentist",
    "department_store",
    "dessert_restaurant",
    "dessert_shop",
    "diner",
    "donut_shop",
    "drugstore",
    "event_venue",
    "farm",
    "fast_food_restaurant",
    "ferry_terminal",
    "fine_dining_restaurant",
    "fitness_center",
    "food",
    "food_court",
    "food_store",
    "french_restaurant",
    "gas_station",
    "general_contractor",
    "gift_shop",
    "golf_course",
    "government_office",
    "greek_restaurant",
    "grocery_store",
    "gym",
    "hamburger_restaurant",
    "health",
    "historical_landmark",
    "hospital",
    "hostel",
    "hotel",
    "ice_cream_shop",
    "ice_skating_rink",
    "indian_restaurant",
    "indonesian_restaurant",
    "international_airport",
    "italian_restaurant",
    "japanese_restaurant",
    "juice_shop",
    "karaoke",
    "korean_restaurant",
    "laundry",
    "lebanese_restaurant",
    "library",
    "light_rail_station",
    "liquor_store",
    "local_government_office",
    "marina",
    "market",
    "meal_delivery",
    "meal_takeaway",
    "mediterranean_restaurant",
    "mexican_restaurant",
    "middle_eastern_restaurant",
    "motel",
    "movie_theater",
    "museum",
    "nail_salon",
    "night_club",
    "observation_deck",
    "park",
    "parking",
    "performing_arts_theater",
    "pet_store",
    "pizza_restaurant",
    "place_of_worship",
    "playground",
    "plaza",
    "point_of_interest",
    "post_office",
    "pub",
    "ramen_restaurant",
    "real_estate_agency",
    "rest_stop",
    "restaurant",
    "sandwich_shop",
    "school",
    "seafood_restaurant",
    "shopping_mall",
    "spa",
    "spanish_restaurant",
    "sporting_goods_store",
    "sports_activity_location",
    "sports_club",
    "sports_complex",
    "steak_house",
    "store",
    "subway_station",
    "supermarket",
    "sushi_restaurant",
    "synagogue",
    "tea_house",
    "thai_restaurant",
    "tour_agency",
    "tourist_attraction",
    "train_station",
    "transit_depot",
    "transit_station",
    "turkish_restaurant",
    "university",
    "vegan_restaurant",
    "vegetarian_restaurant",
    "vietnamese_restaurant",
    "wedding_venue",
    "wellness_center",
    "wholesaler",
    "wine_bar",
    "zoo"
  ],
  "type_counts": {
    "restaurant": 30427,
    "chinese_restaurant": 8784,
    "pizza_restaurant": 6680,
    "mexican_restaurant": 5732,
    "bar": 4495,
    "italian_restaurant": 4337,
    "american_restaurant": 4161,
    "japanese_restaurant": 2876,
    "fast_food_restaurant": 2567,
    "coffee_shop": 2147,
    "deli": 2120,
    "cafe": 1946,
    "thai_restaurant": 1714,
    "sushi_restaurant": 1635,
    "indian_restaurant": 1488,
    "korean_restaurant": 1472,
    "seafood_restaurant": 1445,
    "sandwich_shop": 1248,
    "bakery": 1209,
    "diner": 1190,
    "hamburger_restaurant": 1186,
    "mediterranean_restaurant": 1103,
    "bar_and_grill": 1096,
    "asian_restaurant": 932,
    "french_restaurant": 801,
    "vietnamese_restaurant": 715,
    "steak_house": 665,
    "greek_restaurant": 658,
    "ramen_restaurant": 608,
    "meal_takeaway": 599,
    "hotel": 595,
    "bagel_shop": 550,
    "middle_eastern_restaurant": 545,
    "grocery_store": 485,
    "pub": 480,
    "barbecue_restaurant": 444,
    "breakfast_restaurant": 440,
    "vegan_restaurant": 429,
    "spanish_restaurant": 409,
    "event_venue": 402,
    "wine_bar": 385,
    "turkish_restaurant": 270,
    "fine_dining_restaurant": 265,
    "meal_delivery": 253,
    "juice_shop": 245,
    "buffet_restaurant": 211,
    "market": 194,
    "food_court": 182,
    "vegetarian_restaurant": 175,
    "catering_service": 165,
    "supermarket": 160,
    "dessert_shop": 159,
    "brunch_restaurant": 153,
    "ice_cream_shop": 135,
    "shopping_mall": 125,
    "brazilian_restaurant": 120,
    "lebanese_restaurant": 115,
    "tea_house": 115,
    "banquet_hall": 107,
    "african_restaurant": 104,
    "wholesaler": 100,
    "night_club": 95,
    "park": 90,
    "apartment_building": 88,
    "sports_complex": 85,
    "food_store": 75,
    "hospital": 65,
    "condominium_complex": 61,
    "asian_grocery_store": 60,
    "afghani_restaurant": 60,
    "wedding_venue": 60,
    "dessert_restaurant": 56,
    "acai_shop": 55,
    "subway_station": 55,
    "corporate_office": 52,
    "real_estate_agency": 52,
    "bowling_alley": 50,
    "convenience_store": 46,
    "cafeteria": 40,
    "movie_theater": 35,
    "apartment_complex": 35,
    "playground": 30,
    "museum": 30,
    "ice_skating_rink": 30,
    "sports_club": 26,
    "store": 25,
    "butcher_shop": 25,
    "spa": 25,
    "marina": 25,
    "comedy_club": 25,
    "indonesian_restaurant": 20,
    "historical_landmark": 20,
    "performing_arts_theater": 20,
    "food": 20,
    "clothing_store": 20,
    "book_store": 19,
    "gym": 15,
    "athletic_field": 15,
    "cultural_center": 15,
    "department_store": 15,
    "concert_hall": 15,
    "government_office": 15,
    "sports_activity_location": 15,
    "donut_shop": 15,
    "gas_station": 15,
    "synagogue": 15,
    "amusement_center": 15,
    "point_of_interest": 14,
    "parking": 12,
    "child_care_agency": 11,
    "tour_agency": 10,
    "consultant": 10,
    "transit_depot": 10,
    "plaza": 10,
    "international_airport": 10,
    "bus_station": 10,
    "health": 10,
    "local_government_office": 10,
    "confectionery": 10,
    "farm": 10,
    "motel": 10,
    "zoo": 10,
    "golf_course": 10,
    "drugstore": 10,
    "liquor_store": 10,
    "wellness_center": 9,
    "tourist_attraction": 8,
    "train_station": 5,
    "karaoke": 5,
    "observation_deck": 5,
    "ferry_terminal": 5,
    "arena": 5,
    "light_rail_station": 5,
    "transit_station": 5,
    "art_gallery": 5,
    "post_office": 5,
    "botanical_garden": 5,
    "laundry": 5,
    "casino": 5,
    "fitness_center": 5,
    "dentist": 5,
    "library": 5,
    "chocolate_shop": 5,
    "university": 5,
    "pet_store": 5,
    "general_contractor": 5,
    "nail_salon": 5,
    "rest_stop": 5,
    "place_of_worship": 5,
    "courier_service": 5,
    "hostel": 5,
    "amphitheatre": 5,
    "gift_shop": 5,
    "school": 2,
    "sporting_goods_store": 2
  }
}